setup.py
ship/__init__.py
ship/config.py
ship/db.py
ship/load.py
ship.egg-info/PKG-INFO
ship.egg-info/SOURCES.txt
ship.egg-info/dependency_links.txt
ship.egg-info/requires.txt
ship.egg-info/top_level.txt
ship/tests/__init__.py
ship/tests/test_db.py