Metadata-Version: 1.0
Name: ship
Version: 0.1
Summary: Swiss Health Insurance Premiums
Home-page: http://pypi.python.org/pypi/ship/
Author: Denis Krienbühl
Author-email: denis.krienbuehl@gmail.com
License: LICENSE.txt
Platform: UNKNOWN
